{
  "Home": "/pages/index",
  "Search": "/pages/search",
  "Articles": "/pages/articles/index",
  "ArticleDetails": "/pages/articles/details",
  "ArticleCreate": "/pages/articles/edit",
  "ArticleEdit": "/pages/articles/edit",
  "Forget": "/pages/login/forget",
  "Login": "/pages/login/login",
  "Register": "/pages/login/register",
  "QuizResearch": "/pages/quizzes/search",
  "PuxianExam": "/pages/quizzes/random",
  "QuizDetails": "/pages/quizzes/details",
  "QuizCreate": "/pages/quizzes/index",
  "UserDetails": "/pages/users/details",
  "UserSettings": "/pages/users/settings/information",
  "Certificate": "/pages/users/details",
  "Notification": "/pages/mails/index",
  "Rewards": "/pages/index",
  "RewardsDetails": "/pages/index",
  "AdminRewards": "/pages/index",
  "RewardsTransactions": "/pages/index",
  "WordList": "/pages/lists/index",
  "WordListEditor": "/pages/lists/upload",
  "WordListDetails": "/pages/lists/details",
  "WordDetails": "/pages/words/details",
  "WordCreate": "/pages/words/details",
  "WordEdit": "/pages/words/details",
  "Application": "/pages/words/details",
  "QuickRecording": "/pages/words/pronunciations/upload",
  "RankList": "/pages/words/pronunciations/ranking",
  "Pinyin": "/pages/tools/pinyin",
  "Tools": "/pages/tools/index",
  "Conditions": "/pages/tools/condition",
  "Characters": "/pages/words/characters/details",
  "DailyExpressions": "/pages/tools/daily-expression/index",
  "RecordConfirming": "/pages/words/pronunciations",
  "WordConfirming": "/pages/words/details",
  "Relative": "/pages/tools/relative",
  "Dictionary": "/pages/tools/dictionary",
  "Translation": "/pages/index",
  "ptxTranslation": "/pages/index",
  "xtpTranslation": "/pages/index",
  "Music": "/pages/index",
  "About": "/pages/index"
}
